justproj_toolkit/__main__.py
justproj_toolkit/baseproject/documentation.py
justproj_toolkit/utils.py
justproj_toolkit-0.1.2.dist-info/METADATA
justproj_toolkit-0.1.2.dist-info/WHEEL
justproj_toolkit-0.1.2.dist-info/RECORD
